obscura_client/__init__.py
obscura_client/client.py
obscura_client/config_map.py
obscura_client-0.1.0.dist-info/METADATA
obscura_client-0.1.0.dist-info/WHEEL
obscura_client-0.1.0.dist-info/RECORD
